sardana_tango/__init__.py
sardana_tango/_version.py
sardana_tango/ctrl/TangoAttrCTCtrl.py
sardana_tango/ctrl/TangoAttrIORCtrl.py
sardana_tango/ctrl/TangoAttrMotorCtrl.py
sardana_tango/ctrl/TangoAttrOneDCtrl.py
sardana_tango/ctrl/TangoAttrZeroDCtrl.py
sardana_tango/ctrl/__init__.py
sardana_tango-0.4.0.dist-info/licenses/LICENSE
sardana_tango-0.4.0.dist-info/METADATA
sardana_tango-0.4.0.dist-info/WHEEL
sardana_tango-0.4.0.dist-info/top_level.txt
sardana_tango-0.4.0.dist-info/RECORD
