Metadata-Version: 2.4
Name: sardana_tango
Version: 0.4.0
Summary: sardana tango controllers & macros
Author-email: Sardana Controller Developers <sardana-devel@lists.sourceforge.net>
Maintainer-email: ALBA <sardana-devel@lists.sourceforge.net>
License: GPL-3.0-or-later
Project-URL: Homepage, https://gitlab.com/sardana-org/sardana-tango
Project-URL: Repository, https://gitlab.com/sardana-org/sardana-tango
Keywords: tango,sardana
Classifier: Development Status :: 4 - Beta
Classifier: Intended Audience :: Developers
Classifier: License :: OSI Approved :: GNU General Public License v3 (GPLv3)
Classifier: Natural Language :: English
Classifier: Operating System :: POSIX
Classifier: Programming Language :: Python :: 3
Classifier: Programming Language :: Python :: 3 :: Only
Classifier: Programming Language :: Python :: 3.5
Classifier: Programming Language :: Python :: 3.6
Classifier: Programming Language :: Python :: 3.7
Classifier: Programming Language :: Python :: 3.8
Classifier: Programming Language :: Python :: 3.9
Classifier: Programming Language :: Python :: 3.10
Classifier: Programming Language :: Python :: 3.11
Classifier: Programming Language :: Python :: 3.12
Requires-Python: >=3.5
License-File: LICENSE
Requires-Dist: sardana
Requires-Dist: pytango
Provides-Extra: tests
Requires-Dist: pytest; extra == "tests"
Dynamic: license-file
